Metadata-Version: 2.1
Name: iosense
Version: 0.0.8
Summary: I/O Sense Data Access Library
Home-page: UNKNOWN
Author: Faclon Labs Private Limited
Author-email: <rishi.sharma@faclon.com>
License: UNKNOWN
Keywords: python,faclon,iosense,data
Platform: UNKNOWN
Classifier: Development Status :: 1 - Planning
Classifier: Intended Audience :: Developers
Classifier: Programming Language :: Python :: 3
Classifier: Operating System :: Unix
Classifier: Operating System :: MacOS :: MacOS X
Classifier: Operating System :: Microsoft :: Windows
